PyPIC3D/J.py
PyPIC3D/__init__.py
PyPIC3D/__main__.py
PyPIC3D/boris.py
PyPIC3D/boundaryconditions.py
PyPIC3D/errors.py
PyPIC3D/evolve.py
PyPIC3D/experiment.py
PyPIC3D/initialization.py
PyPIC3D/particle.py
PyPIC3D/plotting.py
PyPIC3D/rho.py
PyPIC3D/utils.py
pypic3d-0.1.3.dist-info/licenses/LICENSE
pypic3d-0.1.3.dist-info/METADATA
pypic3d-0.1.3.dist-info/WHEEL
pypic3d-0.1.3.dist-info/entry_points.txt
pypic3d-0.1.3.dist-info/top_level.txt
pypic3d-0.1.3.dist-info/RECORD
