Metadata-Version: 2.4
Name: PyPIC3D
Version: 0.1.3
Summary: A 3D Particle-In-Cell simulation package
Author-email: Christopher Woolford <clwoolford@wisc.edu>
License: MIT License
License-File: LICENSE
Requires-Dist: jax
Requires-Dist: matplotlib
Requires-Dist: plotly
Requires-Dist: toml
Requires-Dist: tqdm
Requires-Dist: epyc
Requires-Dist: pyevtk
Requires-Dist: vtk
Dynamic: license-file
